pagesaver/__init__.py
pagesaver/constants.py
pagesaver/enums.py
pagesaver/manage.py
pagesaver/settings.py
pagesaver/authorization/__init__.py
pagesaver/authorization/admin.py
pagesaver/authorization/apps.py
pagesaver/authorization/models.py
pagesaver/authorization/migrations/0001_initial.py
pagesaver/authorization/migrations/__init__.py
pagesaver/cli/__init__.py
pagesaver/cli/export.py
pagesaver/cli/init.py
pagesaver/cli/server.py
pagesaver/cli/types.py
pagesaver/core/__init__.py
pagesaver/core/api.py
pagesaver/core/asgi.py
pagesaver/core/settings.py
pagesaver/core/urls.py
pagesaver/core/wsgi.py
pagesaver/lib/__init__.py
pagesaver/lib/base/__init__.py
pagesaver/lib/base/client.py
pagesaver/lib/base/models.py
pagesaver/lib/notion/__init__.py
pagesaver/lib/notion/block.py
pagesaver/lib/notion/client.py
pagesaver/lib/notion/property.py
pagesaver/record/__init__.py
pagesaver/record/admin.py
pagesaver/record/api.py
pagesaver/record/models.py
pagesaver/record/tasks.py
pagesaver/record/migrations/0001_initial.py
pagesaver/record/migrations/__init__.py
pagesaver/record/runner/__init__.py
pagesaver/record/runner/base.py
pagesaver/record/runner/thread.py
pagesaver/utils/__init__.py
pagesaver/utils/datetime_utils.py
pagesaver/utils/export_utils.py
pagesaver/utils/notion_utils.py
pagesaver-0.1.0.dist-info/LICENSE
pagesaver-0.1.0.dist-info/METADATA
pagesaver-0.1.0.dist-info/WHEEL
pagesaver-0.1.0.dist-info/entry_points.txt
pagesaver-0.1.0.dist-info/top_level.txt
pagesaver-0.1.0.dist-info/RECORD
