Metadata-Version: 2.1
Name: pagesaver
Version: 0.1.0
Summary: Archive your web page.
Home-page: https://github.com/ZhaoQi99/PageSaver
Author: Qi Zhao
Author-email: zhaoqi99@outlook.com
Project-URL: Homepage, https://github.com/ZhaoQi99/PageSaver
Project-URL: Changelog, https://github.com/ZhaoQi99/PageSaver/releases
Project-URL: Source, https://github.com/ZhaoQi99/PageSaver
Project-URL: Issue Tracker, https://github.com/ZhaoQi99/PageSaver/issues
Keywords: archiving,web archiving,playwright,backup
Classifier: License :: OSI Approved :: GNU General Public License v3 (GPLv3)
Classifier: Programming Language :: Python :: Implementation :: CPython
Classifier: Programming Language :: Python :: 3
Requires-Python: >=3.8
License-File: LICENSE
Requires-Dist: django
Requires-Dist: django-ninja
Requires-Dist: click
Requires-Dist: requests
Requires-Dist: hypercorn
Requires-Dist: playwright
